requests_forecast.py
requests_forecast-1.0.0.dist-info/AUTHORS.rst
requests_forecast-1.0.0.dist-info/LICENSE
requests_forecast-1.0.0.dist-info/METADATA
requests_forecast-1.0.0.dist-info/WHEEL
requests_forecast-1.0.0.dist-info/top_level.txt
requests_forecast-1.0.0.dist-info/RECORD
