Metadata-Version: 2.1
Name: requests-forecast
Version: 1.0.0
Summary: A minimalist Forecast.io API client.
Home-page: https://github.com/jefftriplett/requests-forecast
Author: Jeff Triplett
Author-email: jeff.triplett@gmail.com
License: BSD
Platform: UNKNOWN
Classifier: Intended Audience :: Developers
Classifier: License :: OSI Approved :: BSD License
Classifier: Operating System :: OS Independent
Classifier: Programming Language :: Python
Classifier: Programming Language :: Python :: 3
Classifier: Programming Language :: Python :: 3.6
Classifier: Programming Language :: Python :: 3.7
Classifier: Programming Language :: Python :: 3.8
Classifier: Programming Language :: Python :: 3.9
Classifier: Programming Language :: Python :: 3.10
Classifier: Programming Language :: Python :: Implementation :: CPython
Classifier: Topic :: Internet :: WWW/HTTP :: Dynamic Content
Classifier: Topic :: Software Development :: Libraries :: Python Modules
Requires-Python: >=3.6.1
License-File: LICENSE
License-File: AUTHORS.rst
Requires-Dist: pytz
Requires-Dist: requests
